cvvideoplayer/__init__.py
cvvideoplayer/frame_reader.py
cvvideoplayer/icon.png
cvvideoplayer/recorder.py
cvvideoplayer/display_managers/__init__.py
cvvideoplayer/display_managers/abstract_display_manager.py
cvvideoplayer/display_managers/linux_display_manager.py
cvvideoplayer/display_managers/windows_display_manager.py
cvvideoplayer/frame_editors/__init__.py
cvvideoplayer/frame_editors/background_substraction.py
cvvideoplayer/frame_editors/base_bbox_plotter.py
cvvideoplayer/frame_editors/base_frame_edit_callback.py
cvvideoplayer/frame_editors/detections_csv_plotter.py
cvvideoplayer/frame_editors/fit_frame_to_screen.py
cvvideoplayer/frame_editors/frame_info_overlay.py
cvvideoplayer/frame_editors/frame_normlizer.py
cvvideoplayer/frame_editors/frame_snapshot.py
cvvideoplayer/frame_editors/histogram_equalizer.py
cvvideoplayer/frame_editors/key_map_overlay.py
cvvideoplayer/frame_editors/optical_flow_plotter.py
cvvideoplayer/input_management/__init__.py
cvvideoplayer/input_management/base_input_parser.py
cvvideoplayer/input_management/input_handler.py
cvvideoplayer/input_management/linux_input_parser.py
cvvideoplayer/input_management/windows_input_parser.py
cvvideoplayer/utils/__init__.py
cvvideoplayer/utils/bbox_utils.py
cvvideoplayer/utils/drawing_utils.py
cvvideoplayer/utils/linux_os_utils.py
cvvideoplayer/utils/ui_utils.py
cvvideoplayer/utils/video_player_utils.py
cvvideoplayer/utils/windows_os_utils.py
cvvideoplayer/video_players/__init__.py
cvvideoplayer/video_players/base_video_player.py
cvvideoplayer/video_players/create_video_player.py
cvvideoplayer/video_players/double_frame_video_player.py
cvvideoplayer/video_players/windows_video_player.py
cvvideoplayer-1.2.9.dist-info/METADATA
cvvideoplayer-1.2.9.dist-info/WHEEL
cvvideoplayer-1.2.9.dist-info/top_level.txt
cvvideoplayer-1.2.9.dist-info/RECORD
