Metadata-Version: 2.1
Name: cvvideoplayer
Version: 1.2.9
Summary: moduler multi purpose video player for debugging algorithms in python
Author: Daniel Tomer
Author-email: danieltomer1@gmail.com
Project-URL: Homepage, https://github.com/danieltomer1/CVVideoPlayer
Keywords: opencv,video,player,video player,cvvideoplayer,computer vision,image processing,customizable
Classifier: Programming Language :: Python :: 3
Classifier: License :: OSI Approved :: MIT License
Requires-Python: >=3.8
Requires-Dist: numpy
Requires-Dist: opencv-python
Requires-Dist: pynput
Requires-Dist: matplotlib
Requires-Dist: python-xlib; platform_system == "Linux"
Requires-Dist: pywin32; platform_system == "Windows"
